create_sap_table/__init__.py
create_sap_table/create_table_leanx.py
create_sap_table-0.0.2.dist-info/METADATA
create_sap_table-0.0.2.dist-info/WHEEL
create_sap_table-0.0.2.dist-info/licenses/LICENSE
create_sap_table-0.0.2.dist-info/RECORD
