Metadata-Version: 2.1
Name: create_sap_table
Version: 0.0.2
Summary: Create SQL script to generate SQL tables by using table names.
Project-URL: Homepage, https://github.com/NaolGB/create-sap-table
Project-URL: Bug Tracker, https://github.com/NaolGB/create-sap-table/issues
Author: Naol Basaye
License-File: LICENSE
Classifier: License :: OSI Approved :: MIT License
Classifier: Operating System :: OS Independent
Classifier: Programming Language :: Python :: 3
Requires-Python: >=3.7
Requires-Dist: beautifulsoup4==4.12.2
Requires-Dist: requests==2.31.0
